pyomo_symmetry
